
<?xml version="1.0" encoding="UTF-8"?>

<dolfin xmlns:dolfin="http://www.fenicsproject.org">
  <mesh celltype="triangle" dim="2">
    <vertices size="24712">
      <vertex index="0" x="0.0000000000000000e+00" y="0.0000000000000000e+00" z="0.0000000000000000e+00"/>
      <vertex index="1" x="6.8784531055099997e-03" y="1.1305973587200001e-02" z="0.0000000000000000e+00"/>
      <vertex index="2" x="1.2598065408799999e-02" y="1.5295308021200001e-02" z="0.0000000000000000e+00"/>
      <vertex index="3" x="1.8125664330499999e-02" y="1.8072316635400001e-02" z="0.0000000000000000e+00"/>
      <vertex index="4" x="2.3553105257099999e-02" y="2.0216952013200000e-02" z="0.0000000000000000e+00"/>
      <vertex index="5" x="2.8915979669700002e-02" y="2.1953930114999999e-02" z="0.0000000000000000e+00"/>
      <vertex index="6" x="3.4232550541000002e-02" y="2.3398558912000000e-02" z="0.0000000000000000e+00"/>
      <vertex index="7" x="3.9513674741600002e-02" y="2.4619386045999999e-02" z="0.0000000000000000e+00"/>
      <vertex index="8" x="4.4766432768399998e-02" y="2.5661116053900000e-02" z="0.0000000000000000e+00"/>
      <vertex index="9" x="4.9995748511999998e-02" y="2.6554837183100002e-02" z="0.0000000000000000e+00"/>
      <vertex index="10" x="5.5205212098900003e-02" y="2.7323216620200000e-02" z="0.0000000000000000e+00"/>
      <vertex index="11" x="6.0397538304999998e-02" y="2.7983394800900001e-02" z="0.0000000000000000e+00"/>
      <vertex index="12" x="6.5574840309800000e-02" y="2.8548713825900001e-02" z="0.0000000000000000e+00"/>
      <vertex index="13" x="7.0738802304899998e-02" y="2.9029807272300000e-02" z="0.0000000000000000e+00"/>
      <vertex index="14" x="7.5890793197900000e-02" y="2.9435318089400000e-02" z="0.0000000000000000e+00"/>
      <vertex index="15" x="8.1031944261700004e-02" y="2.9772388860099998e-02" z="0.0000000000000000e+00"/>
      <vertex index="16" x="8.6163203790400003e-02" y="3.0047006882600001e-02" z="0.0000000000000000e+00"/>
      <vertex index="17" x="9.1285376572999996e-02" y="3.0264253398800001e-02" z="0.0000000000000000e+00"/>
      <vertex index="18" x="9.6399153042000002e-02" y="3.0428487631399999e-02" z="0.0000000000000000e+00"/>
      <vertex index="19" x="1.0150513121700000e-01" y="3.0543485333100001e-02" z="0.0000000000000000e+00"/>
      <vertex index="20" x="1.0660383351000000e-01" y="3.0612544879499999e-02" z="0.0000000000000000e+00"/>
      <vertex index="21" x="1.1169571978400000e-01" y="3.0638569740999998e-02" z="0.0000000000000000e+00"/>
      <vertex index="22" x="1.1678119764700000e-01" y="3.0624133459600002e-02" z="0.0000000000000000e+00"/>
      <vertex index="23" x="1.2186063066100000e-01" y="3.0571531464400000e-02" z="0.0000000000000000e+00"/>
      <vertex index="24" x="1.2693434495200001e-01" y="3.0482822843199999e-02" z="0.0000000000000000e+00"/>
      <vertex index="25" x="1.3200263460200001e-01" y="3.0359864354199999e-02" z="0.0000000000000000e+00"/>
      <vertex index="26" x="1.3706576607099999e-01" y="3.0204338366800001e-02" z="0.0000000000000000e+00"/>
      <vertex index="27" x="1.4212398186600000e-01" y="3.0017776009500001e-02" z="0.0000000000000000e+00"/>
      <vertex index="28" x="1.4717750360000001e-01" y="2.9801576489799999e-02" z="0.0000000000000000e+00"/>
      <vertex index="29" x="1.5222653456300000e-01" y="2.9557023334199999e-02" z="0.0000000000000000e+00"/>
      <vertex index="30" x="1.5727126189900001e-01" y="2.9285298128000001e-02" z="0.0000000000000000e+00"/>
      <vertex index="31" x="1.6231185846000001e-01" y="2.8987492208599999e-02" z="0.0000000000000000e+00"/>
      <vertex index="32" x="1.6734848438700001e-01" y="2.8664616674400002e-02" z="0.0000000000000000e+00"/>
      <vertex index="33" x="1.7238128847900000e-01" y="2.8317610995700002e-02" z="0.0000000000000000e+00"/>
      <vertex index="34" x="1.7741040936600000e-01" y="2.7947350460099999e-02" z="0.0000000000000000e+00"/>
    </cells>
  </mesh>
</dolfin>
<?xml version="1.0" encoding="UTF-8"?>

<dolfin xmlns:dolfin="http://www.fenicsproject.org">
  <mesh celltype="triangle" dim="2">
    <vertices size="24712">
      <vertex index="0" x="0.0000000000000000e+00" y="0.0000000000000000e+00" z="0.0000000000000000e+00"/>
      <vertex index="1" x="6.8784531055099997e-03" y="1.1305973587200001e-02" z="0.0000000000000000e+00"/>
      <vertex index="2" x="1.2598065408799999e-02" y="1.5295308021200001e-02" z="0.0000000000000000e+00"/>
      <vertex index="3" x="1.8125664330499999e-02" y="1.8072316635400001e-02" z="0.0000000000000000e+00"/>
      <vertex index="4" x="2.3553105257099999e-02" y="2.0216952013200000e-02" z="0.0000000000000000e+00"/>
      <vertex index="5" x="2.8915979669700002e-02" y="2.1953930114999999e-02" z="0.0000000000000000e+00"/>
      <vertex index="6" x="3.4232550541000002e-02" y="2.3398558912000000e-02" z="0.0000000000000000e+00"/>
      <vertex index="7" x="3.9513674741600002e-02" y="2.4619386045999999e-02" z="0.0000000000000000e+00"/>
      <vertex index="8" x="4.4766432768399998e-02" y="2.5661116053900000e-02" z="0.0000000000000000e+00"/>
      <vertex index="9" x="4.9995748511999998e-02" y="2.6554837183100002e-02" z="0.0000000000000000e+00"/>
      <vertex index="10" x="5.5205212098900003e-02" y="2.7323216620200000e-02" z="0.0000000000000000e+00"/>
      <vertex index="11" x="6.0397538304999998e-02" y="2.7983394800900001e-02" z="0.0000000000000000e+00"/>
      <vertex index="12" x="6.5574840309800000e-02" y="2.8548713825900001e-02" z="0.0000000000000000e+00"/>
      <vertex index="13" x="7.0738802304899998e-02" y="2.9029807272300000e-02" z="0.0000000000000000e+00"/>
      <vertex index="14" x="7.5890793197900000e-02" y="2.9435318089400000e-02" z="0.0000000000000000e+00"/>
      <vertex index="15" x="8.1031944261700004e-02" y="2.9772388860099998e-02" z="0.0000000000000000e+00"/>
      <vertex index="16" x="8.6163203790400003e-02" y="3.0047006882600001e-02" z="0.0000000000000000e+00"/>
      <vertex index="17" x="9.1285376572999996e-02" y="3.0264253398800001e-02" z="0.0000000000000000e+00"/>
      <vertex index="18" x="9.6399153042000002e-02" y="3.0428487631399999e-02" z="0.0000000000000000e+00"/>
      <vertex index="19" x="1.0150513121700000e-01" y="3.0543485333100001e-02" z="0.0000000000000000e+00"/>
      <vertex index="20" x="1.0660383351000000e-01" y="3.0612544879499999e-02" z="0.0000000000000000e+00"/>
      <vertex index="21" x="1.1169571978400000e-01" y="3.0638569740999998e-02" z="0.0000000000000000e+00"/>
      <vertex index="22" x="1.1678119764700000e-01" y="3.0624133459600002e-02" z="0.0000000000000000e+00"/>
      <vertex index="23" x="1.2186063066100000e-01" y="3.0571531464400000e-02" z="0.0000000000000000e+00"/>
      <vertex index="24" x="1.2693434495200001e-01" y="3.0482822843199999e-02" z="0.0000000000000000e+00"/>
      <vertex index="25" x="1.3200263460200001e-01" y="3.0359864354199999e-02" z="0.0000000000000000e+00"/>
      <vertex index="26" x="1.3706576607099999e-01" y="3.0204338366800001e-02" z="0.0000000000000000e+00"/>
      <vertex index="27" x="1.4212398186600000e-01" y="3.0017776009500001e-02" z="0.0000000000000000e+00"/>
      <vertex index="28" x="1.4717750360000001e-01" y="2.9801576489799999e-02" z="0.0000000000000000e+00"/>
      <vertex index="29" x="1.5222653456300000e-01" y="2.9557023334199999e-02" z="0.0000000000000000e+00"/>
      <vertex index="30" x="1.5727126189900001e-01" y="2.9285298128000001e-02" z="0.0000000000000000e+00"/>
      <vertex index="31" x="1.6231185846000001e-01" y="2.8987492208599999e-02" z="0.0000000000000000e+00"/>
      <vertex index="32" x="1.6734848438700001e-01" y="2.8664616674400002e-02" z="0.0000000000000000e+00"/>
      <vertex index="33" x="1.7238128847900000e-01" y="2.8317610995700002e-02" z="0.0000000000000000e+00"/>
      <vertex index="34" x="1.7741040936600000e-01" y="2.7947350460099999e-02" z="0.0000000000000000e+00"/>
    </cells>
  </mesh>
</dolfin>
